{
  "free_keys": [
    {
      "key": "Kaiz51383826231",
      "key_type": "free",
      "status": "used",
      "device_id": "c838b2c6-231b-4936-970e-42cacd9865a1",
      "shortened_urls": [
        "https://yeumoney.com/nj9qqKWv7a5",
        "https://link2m.com/qT77Yq4s"
      ],
      "created_at": "2025-05-18T18:44:35.689938+07:00",
      "expiration_date": "2025-05-20T18:44:30.725521+07:00",
      "duration_minutes": 2880,
      "is_active": true,
      "disabled": false
    },
    {
      "key": "Kaiz51353740094",
      "key_type": "free",
      "status": "used",
      "device_id": "5ceffbd3-fdd7-4009-a437-cf2c7fe77f45",
      "shortened_urls": [
        "https://yeumoney.com/ZXSKDrvGeg",
        "https://link2m.com/o0OGa5l"
      ],
      "created_at": "2025-05-18T19:46:18.299570+07:00",
      "expiration_date": "2025-05-20T19:46:13.199929+07:00",
      "duration_minutes": 2880,
      "is_active": true,
      "disabled": false
    },
    {
      "key": "Kaiz51339944933",
      "key_type": "free",
      "status": "used",
      "device_id": "39944933-1868-4bd5-a2bb-d31f2e028cc1",
      "shortened_urls": [
        "https://yeumoney.com/kDDaRhW79o7",
        "https://link2m.com/df11Um"
      ],
      "created_at": "2025-05-18T21:21:56.683325+07:00",
      "expiration_date": "2025-05-20T21:21:51.752730+07:00",
      "duration_minutes": 2880,
      "is_active": true,
      "disabled": false
    },
    {
      "key": "Kaiz51320063594",
      "key_type": "free",
      "status": "used",
      "device_id": "200b6cff-3594-4a55-9775-64271ee586b8",
      "shortened_urls": [
        "https://yeumoney.com/YFNDBFpE",
        "https://link2m.com/TeQhG"
      ],
      "created_at": "2025-05-18T21:30:26.744242+07:00",
      "expiration_date": "2025-05-20T21:30:21.414469+07:00",
      "duration_minutes": 2880,
      "is_active": true,
      "disabled": false
    },
    {
      "key": "Kaiz51323",
      "key_type": "free",
      "status": "used",
      "device_id": "SERfNmYwM2RkZWEwYjllMzFkZjBhNGM3ZDY=",
      "shortened_urls": [
        "https://yeumoney.com/hIIr5hIUR",
        "https://link2m.com/jAiAGP"
      ],
      "created_at": "2025-05-18T22:32:54.232243+07:00",
      "expiration_date": "2025-05-20T22:32:49.244292+07:00",
      "duration_minutes": 2880,
      "is_active": true,
      "disabled": false
    },
    {
      "key": "Kaiz54091258745",
      "key_type": "free",
      "status": "used",
      "device_id": "91a2e58b-7454-4878-aad1-519a9da0617e",
      "shortened_urls": [
        "https://yeumoney.com/TkJa1oa",
        "https://link2m.com/XudoRFg"
      ],
      "created_at": "2025-05-19T12:43:32.393626+07:00",
      "expiration_date": "2025-05-21T12:43:27.311056+07:00",
      "duration_minutes": 2880,
      "is_active": true,
      "disabled": false
    },
    {
      "key": "Kaiz54013230414",
      "key_type": "free",
      "status": "used",
      "device_id": "132bd3b0-4f1e-4992-b18e-7e002bf45eaf",
      "shortened_urls": [
        "https://yeumoney.com/0dgsn",
        "https://link2m.com/G6Dtye"
      ],
      "created_at": "2025-05-19T12:53:52.037624+07:00",
      "expiration_date": "2025-05-21T12:53:46.990532+07:00",
      "duration_minutes": 2880,
      "is_active": true,
      "disabled": false
    },
    {
      "key": "Kaiz54002346431",
      "key_type": "free",
      "status": "used",
      "device_id": "0ec23464-b3d1-47c7-8127-03599f6dcdac",
      "shortened_urls": [
        "https://yeumoney.com/M2Io4QrME",
        "https://link2m.com/8CK5NN"
      ],
      "created_at": "2025-05-19T13:01:27.900805+07:00",
      "expiration_date": "2025-05-21T13:01:22.677472+07:00",
      "duration_minutes": 2880,
      "is_active": true,
      "disabled": false
    },
    {
      "key": "Kaiz54030550519",
      "key_type": "free",
      "status": "used",
      "device_id": "305d5051-9405-4006-b6b2-94bd0f2384f5",
      "shortened_urls": [
        "https://yeumoney.com/02yTS7fq5",
        "https://link2m.com/nc1QEL"
      ],
      "created_at": "2025-05-19T21:26:05.011037+07:00",
      "expiration_date": "2025-05-21T21:25:59.797202+07:00",
      "duration_minutes": 2880,
      "is_active": true,
      "disabled": false
    },
    {
      "key": "Kaiz54053290447",
      "key_type": "free",
      "status": "used",
      "device_id": "532ad9a0-dcf4-47b8-9824-bde40576bf07",
      "shortened_urls": [
        "https://yeumoney.com/8eg4uUt1",
        "https://link2m.com/eZ42Q3R"
      ],
      "created_at": "2025-05-19T22:38:24.652126+07:00",
      "expiration_date": "2025-05-21T22:38:19.597607+07:00",
      "duration_minutes": 2880,
      "is_active": true,
      "disabled": false
    },
    {
      "key": "Kaiz54089886553",
      "key_type": "free",
      "status": "used",
      "device_id": "a8c988b6-5d53-4713-81dc-0ac6064d8d35",
      "shortened_urls": [
        "https://yeumoney.com/GOUUKwMEI",
        "https://link2m.com/Za94ktt"
      ],
      "created_at": "2025-05-19T22:46:27.782644+07:00",
      "expiration_date": "2025-05-21T22:46:22.808401+07:00",
      "duration_minutes": 2880,
      "is_active": true,
      "disabled": false
    },
    {
      "key": "Kaiz54044731837",
      "key_type": "free",
      "status": "used",
      "device_id": "447ae318-a373-49f2-b810-e90668251035",
      "shortened_urls": [
        "https://yeumoney.com/xJc9X",
        "https://link2m.com/VkeijOWS"
      ],
      "created_at": "2025-05-19T23:30:32.045314+07:00",
      "expiration_date": "2025-05-21T23:30:20.979786+07:00",
      "duration_minutes": 2880,
      "is_active": true,
      "disabled": false
    },
    {
      "key": "Kaiz56761486498",
      "key_type": "free",
      "status": "used",
      "device_id": "6fd1d486-4980-4d01-bcf6-104ecd5e654f",
      "shortened_urls": [
        "https://yeumoney.com/DpSmpFih",
        "https://link2m.com/h66WhqU"
      ],
      "created_at": "2025-05-20T06:23:01.026397+07:00",
      "expiration_date": "2025-05-22T06:22:55.866367+07:00",
      "duration_minutes": 2880,
      "is_active": true,
      "disabled": false
    },
    {
      "key": "Kaiz56759808138",
      "key_type": "free",
      "status": "used",
      "device_id": "e598b08d-a138-4733-b342-ced12cd7d5f4",
      "shortened_urls": [
        "https://yeumoney.com/UMs5uOd",
        "https://link2m.com/OeCwWu"
      ],
      "created_at": "2025-05-20T08:19:35.858451+07:00",
      "expiration_date": "2025-05-22T08:19:30.660164+07:00",
      "duration_minutes": 2880,
      "is_active": true,
      "disabled": false
    },
    {
      "key": "Kaiz56723648444",
      "key_type": "free",
      "status": "used",
      "device_id": "e2364dfa-e8ea-4bcb-b4ec-d4adcdc926db",
      "shortened_urls": [
        "https://yeumoney.com/oHKlQCAc6kDW",
        "https://link2m.com/JX5UlI"
      ],
      "created_at": "2025-05-20T16:31:18.595976+07:00",
      "expiration_date": "2025-05-22T16:31:13.584638+07:00",
      "duration_minutes": 2880,
      "is_active": true,
      "disabled": false
    },
    {
      "key": "Kaiz56734179458",
      "key_type": "free",
      "status": "used",
      "device_id": "aa3aadc4-17b9-4ac5-8575-804d9ae1a75d",
      "shortened_urls": [
        "https://yeumoney.com/6e_3dSnB",
        "https://link2m.com/X0HCL"
      ],
      "created_at": "2025-05-20T17:24:32.212716+07:00",
      "expiration_date": "2025-05-22T17:24:26.937216+07:00",
      "duration_minutes": 2880,
      "is_active": true,
      "disabled": false
    },
    {
      "key": "Kaiz56749157354",
      "key_type": "free",
      "status": "used",
      "device_id": "49a1573f-a5eb-4e2a-91f5-9e13b5a7ae63",
      "shortened_urls": [
        "https://yeumoney.com/KFYtrXHQ",
        "https://link2m.com/9GlH2soH"
      ],
      "created_at": "2025-05-20T20:04:44.257342+07:00",
      "expiration_date": "2025-05-22T20:04:39.205410+07:00",
      "duration_minutes": 2880,
      "is_active": true,
      "disabled": false
    },
    {
      "key": "Kaiz56774059574",
      "key_type": "free",
      "status": "used",
      "device_id": "c7e40595-7aec-4008-830c-0d392508ed36",
      "shortened_urls": [
        "https://yeumoney.com/g3QM0uY",
        "https://link2m.com/MXtb4"
      ],
      "created_at": "2025-05-20T21:10:05.543756+07:00",
      "expiration_date": "2025-05-22T21:10:00.526862+07:00",
      "duration_minutes": 2880,
      "is_active": true,
      "disabled": false
    },
    {
      "key": "Kaiz56790959284",
      "key_type": "free",
      "status": "used",
      "device_id": "9a09c59d-28cd-4f0e-ab8c-f32c2bfb303b",
      "shortened_urls": [
        "https://yeumoney.com/_CqhVANxO",
        "https://link2m.com/NOu7cSZ"
      ],
      "created_at": "2025-05-20T22:24:07.943502+07:00",
      "expiration_date": "2025-05-22T22:24:02.911955+07:00",
      "duration_minutes": 2880,
      "is_active": true,
      "disabled": false
    },
    {
      "key": "Kaiz59447972111",
      "key_type": "free",
      "status": "used",
      "device_id": "4b79e721-b11c-4fb6-bf6d-340877a5512a",
      "shortened_urls": [
        "https://yeumoney.com/FoZc9IqX",
        "https://link2m.com/RZuVxZE"
      ],
      "created_at": "2025-05-21T13:09:08.039467+07:00",
      "expiration_date": "2025-05-23T13:09:02.809943+07:00",
      "duration_minutes": 2880,
      "is_active": true,
      "disabled": false
    },
    {
      "key": "Kaiz59436473304",
      "key_type": "free",
      "status": "used",
      "device_id": "36aadf47-d330-442f-9b43-8a7903de5a9c",
      "shortened_urls": [
        "https://yeumoney.com/T_M3",
        "https://link2m.com/tRAr8C"
      ],
      "created_at": "2025-05-21T16:24:02.084347+07:00",
      "expiration_date": "2025-05-23T16:23:57.036094+07:00",
      "duration_minutes": 2880,
      "is_active": true,
      "disabled": false
    },
    {
      "key": "Kaiz59472012854",
      "key_type": "free",
      "status": "used",
      "device_id": "7201285c-d49d-432b-b948-b61667f7b673",
      "shortened_urls": [
        "https://yeumoney.com/_A_Y8F",
        "https://link2m.com/stB9l1"
      ],
      "created_at": "2025-05-21T18:07:15.620546+07:00",
      "expiration_date": "2025-05-23T18:07:10.552909+07:00",
      "duration_minutes": 2880,
      "is_active": true,
      "disabled": false
    },
    {
      "key": "Kaiz59416277886",
      "key_type": "free",
      "status": "used",
      "device_id": "1627e7f8-86e6-4efc-81b5-c7b613fd73f1",
      "shortened_urls": [
        "https://yeumoney.com/fSDzBM",
        "https://link2m.com/d0U1Oh9"
      ],
      "created_at": "2025-05-21T19:20:05.343173+07:00",
      "expiration_date": "2025-05-23T19:20:00.313741+07:00",
      "duration_minutes": 2880,
      "is_active": true,
      "disabled": false
    },
    {
      "key": "Kaiz59425502",
      "key_type": "free",
      "status": "used",
      "device_id": "SERfZTA2Zjk5MDg5Nzg0MTlkYjAxM2FjNmI=",
      "shortened_urls": [
        "https://yeumoney.com/Q6abkCg",
        "https://link2m.com/BmhhQE2"
      ],
      "created_at": "2025-05-21T20:55:15.002116+07:00",
      "expiration_date": "2025-05-23T20:55:10.033498+07:00",
      "duration_minutes": 2880,
      "is_active": true,
      "disabled": false
    }
  ],
  "blacklisted_devices": [],
  "device_active": [
    {
      "device_id": "7f71badc-b565-43b7-8512-65431358eb4a",
      "zalo_id": "1314348804758290347",
      "zalo_name": "N/A",
      "added_at": "2025-05-20T21:34:11.260786+07:00"
    },
    {
      "device_id": "e2364dfa-e8ea-4bcb-b4ec-d4adcdc926db",
      "zalo_id": "7135226684106798739",
      "zalo_name": "N/A",
      "added_at": "2025-05-20T21:39:42.278861+07:00"
    },
    {
      "device_id": "49a1573f-a5eb-4e2a-91f5-9e13b5a7ae63",
      "zalo_id": "1388822385810589136",
      "zalo_name": "N/A",
      "added_at": "2025-05-20T21:48:25.656163+07:00"
    },
    {
      "device_id": "1627e7f8-86e6-4efc-81b5-c7b613fd73f1",
      "zalo_id": "2400893426918875335",
      "zalo_name": "N/A",
      "added_at": "2025-05-20T21:52:30.096696+07:00"
    },
    {
      "device_id": "a8c988b6-5d53-4713-81dc-0ac6064d8d35",
      "zalo_id": "4864811497832173589",
      "zalo_name": "N/A",
      "added_at": "2025-05-20T21:58:19.365416+07:00"
    },
    {
      "device_id": "305d5051-9405-4006-b6b2-94bd0f2384f5",
      "zalo_id": "1025137037436036268",
      "zalo_name": "N/A",
      "added_at": "2025-05-20T22:03:32.602232+07:00"
    },
    {
      "device_id": "c7e40595-7aec-4008-830c-0d392508ed36",
      "zalo_id": "4864811497832173589",
      "zalo_name": "N/A",
      "added_at": "2025-05-20T22:06:08.906921+07:00"
    },
    {
      "device_id": "aa3aadc4-17b9-4ac5-8575-804d9ae1a75d",
      "zalo_id": "2211849985264106532",
      "zalo_name": "N/A",
      "added_at": "2025-05-20T22:10:22.804158+07:00"
    },
    {
      "device_id": "9a09c59d-28cd-4f0e-ab8c-f32c2bfb303b",
      "zalo_id": "3983068311704625616",
      "zalo_name": "N/A",
      "added_at": "2025-05-20T22:13:18.781273+07:00"
    },
    {
      "device_id": "7201285c-d49d-432b-b948-b61667f7b673",
      "zalo_id": "9055601867524261437",
      "zalo_name": "N/A",
      "added_at": "2025-05-20T22:20:32.556477+07:00"
    },
    {
      "device_id": "0ec23464-b3d1-47c7-8127-03599f6dcdac",
      "zalo_id": "1417532653052342074",
      "zalo_name": "N/A",
      "added_at": "2025-05-20T22:28:35.143139+07:00"
    },
    {
      "device_id": "5ceffbd3-fdd7-4009-a437-cf2c7fe77f45",
      "zalo_id": "5021742155516798246",
      "zalo_name": "N/A",
      "added_at": "2025-05-20T22:45:53.427537+07:00"
    },
    {
      "device_id": "df7cbcda-6e87-46f9-ba49-a02d64485ca8",
      "zalo_id": "4864811497832173589",
      "zalo_name": "N/A",
      "added_at": "2025-05-21T09:09:24.416925+07:00"
    },
    {
      "device_id": "5db21d6c-24d0-40c9-afa7-5b58cb3a234b",
      "zalo_id": "4864811497832173589",
      "zalo_name": "N/A",
      "added_at": "2025-05-21T11:32:39.682738+07:00"
    },
    {
      "device_id": "e598b08d-a138-4733-b342-ced12cd7d5f4",
      "zalo_id": "4864811497832173589",
      "zalo_name": "N/A",
      "added_at": "2025-05-21T12:50:11.192911+07:00"
    },
    {
      "device_id": "4b79e721-b11c-4fb6-bf6d-340877a5512a",
      "zalo_id": "1388822385810589136",
      "zalo_name": "N/A",
      "added_at": "2025-05-21T12:52:54.639423+07:00"
    },
    {
      "device_id": "65f20089-de71-459a-b3a2-d70bf3df4b89",
      "zalo_id": "4382340104301247815",
      "zalo_name": "N/A",
      "added_at": "2025-05-21T15:09:47.287601+07:00"
    },
    {
      "device_id": "36aadf47-d330-442f-9b43-8a7903de5a9c",
      "zalo_id": "5029059596233383772",
      "zalo_name": "N/A",
      "added_at": "2025-05-21T15:11:23.959813+07:00"
    },
    {
      "device_id": "SERfZTA2Zjk5MDg5Nzg0MTlkYjAxM2FjNmI=",
      "zalo_id": "3069411608553431566",
      "zalo_name": "N/A",
      "added_at": "2025-05-21T20:46:12.814487+07:00"
    },
    {
      "device_id": "52bf16b2-84c5-45e9-a304-4b4fc4c80f77",
      "zalo_id": "8183569119456980999",
      "zalo_name": "N/A",
      "added_at": "2025-05-21T20:50:19.509630+07:00"
    },
    {
      "device_id": "c536bd1b-ed4d-4462-9451-2069f4e262ab",
      "zalo_id": "8183569119456980999",
      "zalo_name": "N/A",
      "added_at": "2025-05-21T21:00:12.342862+07:00"
    },
    {
      "device_id": "SERfNjNhMTAyNjFkZDAyZWRjNTA2NjRjMzI=",
      "zalo_id": "8470847237443021592",
      "zalo_name": "N/A",
      "added_at": "2025-05-21T21:09:08.380767+07:00"
    }
  ]
}